{
  "postalCodeMappings": {
    "B0E": { "latitude": 45.9311, "longitude": -60.3282, "region": "Antigonish County" },
    "B0H": { "latitude": 44.7311, "longitude": -65.6105, "region": "Annapolis Valley" },
    "B0J": { "latitude": 45.4311, "longitude": -61.9282, "region": "Colchester County" },
    "B0K": { "latitude": 45.1311, "longitude": -64.2282, "region": "Kings County" },
    "B0N": { "latitude": 45.3669, "longitude": -63.2759, "region": "Truro/Colchester" },
    "B0P": { "latitude": 44.9311, "longitude": -64.7282, "region": "Digby County" },
    "B0S": { "latitude": 44.6311, "longitude": -65.7282, "region": "Yarmouth County" },
    "B0T": { "latitude": 43.7311, "longitude": -65.6282, "region": "Shelburne County" },
    "B0V": { "latitude": 44.0311, "longitude": -64.7282, "region": "Queens County" },
    "B0W": { "latitude": 44.3767, "longitude": -64.5233, "region": "Lunenburg County" },
    "B1A": { "latitude": 46.1351, "longitude": -60.1831, "region": "Sydney" },
    "B1B": { "latitude": 46.1351, "longitude": -60.1831, "region": "Sydney" },
    "B1C": { "latitude": 46.1351, "longitude": -60.1831, "region": "Sydney" },
    "B1E": { "latitude": 46.1351, "longitude": -60.1831, "region": "Sydney" },
    "B1G": { "latitude": 46.1351, "longitude": -60.1831, "region": "Sydney" },
    "B1H": { "latitude": 46.1351, "longitude": -60.1831, "region": "Sydney" },
    "B1J": { "latitude": 46.1351, "longitude": -60.1831, "region": "Sydney" },
    "B1K": { "latitude": 46.1351, "longitude": -60.1831, "region": "Sydney" },
    "B1L": { "latitude": 46.1351, "longitude": -60.1831, "region": "Sydney" },
    "B1M": { "latitude": 46.1351, "longitude": -60.1831, "region": "Sydney" },
    "B1N": { "latitude": 46.1351, "longitude": -60.1831, "region": "Sydney" },
    "B1P": { "latitude": 46.1351, "longitude": -60.1831, "region": "Sydney" },
    "B1R": { "latitude": 46.1351, "longitude": -60.1831, "region": "Sydney" },
    "B1S": { "latitude": 46.1351, "longitude": -60.1831, "region": "Sydney" },
    "B1V": { "latitude": 46.1351, "longitude": -60.1831, "region": "Sydney" },
    "B1W": { "latitude": 46.1351, "longitude": -60.1831, "region": "Sydney" },
    "B1X": { "latitude": 46.1351, "longitude": -60.1831, "region": "Sydney" },
    "B1Y": { "latitude": 46.1351, "longitude": -60.1831, "region": "Sydney" },
    "B2A": { "latitude": 46.2000, "longitude": -60.0500, "region": "Glace Bay" },
    "B2C": { "latitude": 46.2000, "longitude": -60.0500, "region": "Glace Bay" },
    "B2G": { "latitude": 46.0500, "longitude": -60.3000, "region": "New Waterford" },
    "B2H": { "latitude": 46.0500, "longitude": -60.3000, "region": "New Waterford" },
    "B2N": { "latitude": 45.8500, "longitude": -60.6000, "region": "Baddeck" },
    "B2R": { "latitude": 45.9000, "longitude": -60.8000, "region": "Ingonish" },
    "B2S": { "latitude": 45.7000, "longitude": -60.9000, "region": "Cheticamp" },
    "B2T": { "latitude": 45.5000, "longitude": -61.0000, "region": "Inverness" },
    "B2V": { "latitude": 45.6000, "longitude": -61.1000, "region": "Port Hawkesbury" },
    "B2W": { "latitude": 45.6500, "longitude": -61.3500, "region": "Antigonish" },
    "B2X": { "latitude": 45.6200, "longitude": -61.9900, "region": "New Glasgow" },
    "B2Y": { "latitude": 44.6680, "longitude": -63.5752, "region": "Dartmouth" },
    "B2Z": { "latitude": 44.6680, "longitude": -63.5752, "region": "Dartmouth" },
    "B3A": { "latitude": 44.6680, "longitude": -63.5752, "region": "Dartmouth" },
    "B3B": { "latitude": 44.6680, "longitude": -63.5752, "region": "Dartmouth" },
    "B3E": { "latitude": 44.6680, "longitude": -63.5752, "region": "Dartmouth" },
    "B3G": { "latitude": 44.6488, "longitude": -63.5752, "region": "Halifax" },
    "B3H": { "latitude": 44.6488, "longitude": -63.5752, "region": "Halifax" },
    "B3J": { "latitude": 44.6488, "longitude": -63.5752, "region": "Halifax" },
    "B3K": { "latitude": 44.6488, "longitude": -63.5752, "region": "Halifax" },
    "B3L": { "latitude": 44.6488, "longitude": -63.5752, "region": "Halifax" },
    "B3M": { "latitude": 44.6488, "longitude": -63.5752, "region": "Halifax" },
    "B3N": { "latitude": 44.6488, "longitude": -63.5752, "region": "Halifax" },
    "B3P": { "latitude": 44.6488, "longitude": -63.5752, "region": "Halifax" },
    "B3R": { "latitude": 44.6488, "longitude": -63.5752, "region": "Halifax" },
    "B3S": { "latitude": 44.6488, "longitude": -63.5752, "region": "Halifax" },
    "B3T": { "latitude": 44.6488, "longitude": -63.5752, "region": "Halifax" },
    "B3V": { "latitude": 44.6488, "longitude": -63.5752, "region": "Halifax" },
    "B3W": { "latitude": 44.6488, "longitude": -63.5752, "region": "Halifax" },
    "B3X": { "latitude": 44.6488, "longitude": -63.5752, "region": "Halifax" },
    "B3Y": { "latitude": 44.6488, "longitude": -63.5752, "region": "Halifax" },
    "B3Z": { "latitude": 44.6488, "longitude": -63.5752, "region": "Halifax" },
    "B4A": { "latitude": 44.6000, "longitude": -63.8000, "region": "Lower Sackville" },
    "B4B": { "latitude": 44.7500, "longitude": -63.6500, "region": "Bedford" },
    "B4C": { "latitude": 44.7500, "longitude": -63.6500, "region": "Bedford" },
    "B4E": { "latitude": 44.7000, "longitude": -63.9000, "region": "Fall River" },
    "B4G": { "latitude": 44.5500, "longitude": -64.2000, "region": "Chester" },
    "B4H": { "latitude": 44.3767, "longitude": -64.5233, "region": "Bridgewater" },
    "B4N": { "latitude": 45.3669, "longitude": -63.2759, "region": "Truro" },
    "B4P": { "latitude": 45.3669, "longitude": -63.2759, "region": "Truro" },
    "B4R": { "latitude": 45.3669, "longitude": -63.2759, "region": "Truro" },
    "B4V": { "latitude": 44.3767, "longitude": -64.5233, "region": "Bridgewater" },
    "B4W": { "latitude": 44.3767, "longitude": -64.5233, "region": "Bridgewater" },
    "B5A": { "latitude": 44.9500, "longitude": -64.4500, "region": "Windsor" },
    "B0M": { "latitude": 44.9500, "longitude": -64.4500, "region": "Windsor" }
  },
  "cityMappings": {
    "halifax": { "latitude": 44.6488, "longitude": -63.5752, "postalCodes": ["B3G", "B3H", "B3J", "B3K", "B3L", "B3M", "B3N", "B3P", "B3R", "B3S", "B3T", "B3V", "B3W", "B3X", "B3Y", "B3Z"] },
    "dartmouth": { "latitude": 44.6680, "longitude": -63.5752, "postalCodes": ["B2Y", "B2Z", "B3A", "B3B", "B3E"] },
    "sydney": { "latitude": 46.1351, "longitude": -60.1831, "postalCodes": ["B1A", "B1B", "B1C", "B1E", "B1G", "B1H", "B1J", "B1K", "B1L", "B1M", "B1N", "B1P", "B1R", "B1S", "B1V", "B1W", "B1X", "B1Y"] },
    "truro": { "latitude": 45.3669, "longitude": -63.2759, "postalCodes": ["B4N", "B4P", "B4R", "B0N"] },
    "bridgewater": { "latitude": 44.3767, "longitude": -64.5233, "postalCodes": ["B4H", "B4V", "B4W", "B0W"] },
    "bedford": { "latitude": 44.7500, "longitude": -63.6500, "postalCodes": ["B4B", "B4C"] },
    "lower sackville": { "latitude": 44.6000, "longitude": -63.8000, "postalCodes": ["B4A"] },
    "new glasgow": { "latitude": 45.6200, "longitude": -61.9900, "postalCodes": ["B2X"] },
    "antigonish": { "latitude": 45.6500, "longitude": -61.3500, "postalCodes": ["B2W", "B0E"] },
    "windsor": { "latitude": 44.9500, "longitude": -64.4500, "postalCodes": ["B5A", "B0M"] },
    "chester": { "latitude": 44.5500, "longitude": -64.2000, "postalCodes": ["B4G"] },
    "glace bay": { "latitude": 46.2000, "longitude": -60.0500, "postalCodes": ["B2A", "B2C"] },
    "new waterford": { "latitude": 46.0500, "longitude": -60.3000, "postalCodes": ["B2G", "B2H"] },
    "baddeck": { "latitude": 45.8500, "longitude": -60.6000, "postalCodes": ["B2N"] },
    "port hawkesbury": { "latitude": 45.6000, "longitude": -61.1000, "postalCodes": ["B2V"] },
    "inverness": { "latitude": 45.5000, "longitude": -61.0000, "postalCodes": ["B2T"] },
    "cheticamp": { "latitude": 45.7000, "longitude": -60.9000, "postalCodes": ["B2S"] },
    "ingonish": { "latitude": 45.9000, "longitude": -60.8000, "postalCodes": ["B2R"] }
  }
}